funfluid/__init__.py
funfluid/common/__init__.py
funfluid/common/base/__init__.py
funfluid/common/base/cache.py
funfluid/common/flow/__init__.py
funfluid/common/particle/__init__.py
funfluid/experiment/__init__.py
funfluid/experiment/chlamydomonas/__init__.py
funfluid/experiment/chlamydomonas/run.py
funfluid/experiment/chlamydomonas/analyse/__init__.py
funfluid/experiment/chlamydomonas/analyse/analyse.py
funfluid/experiment/chlamydomonas/base/__init__.py
funfluid/experiment/chlamydomonas/base/base.py
funfluid/experiment/chlamydomonas/base/globalconfig.py
funfluid/experiment/chlamydomonas/detect/__init__.py
funfluid/experiment/chlamydomonas/detect/background.py
funfluid/experiment/chlamydomonas/detect/contain.py
funfluid/experiment/chlamydomonas/detect/particle.py
funfluid/experiment/chlamydomonas/plot/__init__.py
funfluid/experiment/chlamydomonas/plot/core.py
funfluid/experiment/chlamydomonas/plot/property.py
funfluid/experiment/chlamydomonas/progress/__init__.py
funfluid/experiment/chlamydomonas/progress/video_progress.py
funfluid/experiment/chlamydomonas/utils/__init__.py
funfluid/experiment/chlamydomonas/utils/msd.py
funfluid/lbm/__init__.py
funfluid/lbm/obs_array.py
funfluid/lbm/params.py
funfluid/lbm/core/__init__.py
funfluid/lbm/core/buff.py
funfluid/lbm/core/lattice.py
funfluid/lbm/core/shape.py
funfluid/lbm/core/speed_nb.py
funfluid/lbm/example/__init__.py
funfluid/lbm/example/example_cavity1.py
funfluid/lbm/example/example_cavity3.py
funfluid/lbm/example/example_obstacle.py
funfluid/lbm/example/example_poiseuille.py
funfluid/lbm/example/example_turek.py
funfluid/simulate/__init__.py
funfluid/simulate/ellipse/__init__.py
funfluid/simulate/ellipse/analyse.py
funfluid/simulate/ellipse/plot.py
funfluid/simulate/ellipse/example/__init__.py
funfluid/simulate/ellipse/example/largs_plot_example.py
funfluid/simulate/ellipse/project/__init__.py
funfluid/simulate/ellipse/project/example.py
funfluid/simulate/ellipse/project/project.py
funfluid-202308192123.dist-info/LICENSE
funfluid-202308192123.dist-info/METADATA
funfluid-202308192123.dist-info/WHEEL
funfluid-202308192123.dist-info/top_level.txt
funfluid-202308192123.dist-info/RECORD
