Metadata-Version: 2.1
Name: funfluid
Version: 202308192123
Summary: funfluid
Home-page: https://github.com/1007530194
Author: bingtao
Author-email: 1007530194@qq.com
License-File: LICENSE
Requires-Dist: numpy
Requires-Dist: scipy
Requires-Dist: pandas
Requires-Dist: matplotlib
